{
  "schema_version": 1,
  "location": {
    "name": "Toronto Pearson International Airport",
    "city": "Toronto",
    "province": "Ontario",
    "country": "Canada",
    "climate_identifier": "6158731",
    "station_code": "YYZ",
    "latitude": 43.677,
    "longitude": -79.631
  },
  "definition": "Day-1 means the following local calendar day's maximum temperature, captured once daily at the scheduled workflow time.",
  "forecasts": {
    "2026-07-18": {
      "target_date": "2026-07-18",
      "forecast_capture_date": "2026-07-17",
      "captured_at": "2026-07-17T16:10:50-04:00",
      "lead_definition": "Following local calendar day (Day-1)",
      "providers": [
        {
          "provider_id": "open_meteo_best_match",
          "agency": "Open-Meteo",
          "model": "Best Match",
          "forecast_high_c": 32.3
        },
        {
          "provider_id": "eccc_gem",
          "agency": "Environment and Climate Change Canada",
          "model": "GEM Seamless",
          "forecast_high_c": 27.0
        },
        {
          "provider_id": "noaa_gfs",
          "agency": "NOAA",
          "model": "GFS",
          "forecast_high_c": 32.3
        },
        {
          "provider_id": "ecmwf_ifs",
          "agency": "ECMWF",
          "model": "IFS",
          "forecast_high_c": 27.2
        },
        {
          "provider_id": "dwd_icon",
          "agency": "Deutscher Wetterdienst",
          "model": "ICON Global",
          "forecast_high_c": 28.2
        },
        {
          "provider_id": "meteofrance_arpege",
          "agency": "Météo-France",
          "model": "ARPEGE World",
          "forecast_high_c": 28.1
        },
        {
          "provider_id": "jma_gsm",
          "agency": "Japan Meteorological Agency",
          "model": "GSM",
          "forecast_high_c": 24.8
        }
      ],
      "unavailable": []
    }
  },
  "last_capture_at": "2026-07-17T16:10:50-04:00"
}
